cursetup/__init__.py
cursetup/tester.py
cursetup-0.0.5.dist-info/LICENSE
cursetup-0.0.5.dist-info/METADATA
cursetup-0.0.5.dist-info/WHEEL
cursetup-0.0.5.dist-info/top_level.txt
cursetup-0.0.5.dist-info/RECORD
